setup.py
django_model_validator.egg-info/PKG-INFO
django_model_validator.egg-info/SOURCES.txt
django_model_validator.egg-info/dependency_links.txt
django_model_validator.egg-info/not-zip-safe
django_model_validator.egg-info/requires.txt
django_model_validator.egg-info/top_level.txt
model_validator/__init__.py
model_validator/mixins.py