Metadata-Version: 1.0
Name: django-model-validator
Version: 0.1
Summary: A Django Mixin capable of converting dictionaries of data or lists of dictionaries, to clean Django model instances
Home-page: https://github.com/stargazer/django-model-validator/
Author: C. Paschalides
Author-email: already.late@gmail.com
License: WTFPL
Platform: UNKNOWN
Classifier: Programming Language :: Python
Classifier: Operating System :: OS Independent
Classifier: Topic :: Internet :: WWW/HTTP
Classifier: Framework :: Django
Classifier: Intended Audience :: Developers
Classifier: License :: Freely Distributable
